{ "frames": [
   {
    "filename": "fishtank 0.ase",
    "frame": { "x": 0, "y": 0, "w": 16, "h": 48 },
    "rotated": false,
    "trimmed": false,
    "spriteSourceSize": { "x": 0, "y": 0, "w": 16, "h": 48 },
    "sourceSize": { "w": 16, "h": 48 }
   },
   {
    "filename": "fishtank 1.ase",
    "frame": { "x": 16, "y": 0, "w": 16, "h": 48 },
    "rotated": false,
    "trimmed": false,
    "spriteSourceSize": { "x": 0, "y": 0, "w": 16, "h": 48 },
    "sourceSize": { "w": 16, "h": 48 }
   },
   {
    "filename": "fishtank 2.ase",
    "frame": { "x": 32, "y": 0, "w": 16, "h": 48},
    "rotated": false,
    "trimmed": false,
    "spriteSourceSize": { "x": 0, "y": 0, "w": 16, "h": 48},
    "sourceSize": { "w": 16, "h": 48 }
   }
 ],
 "meta": {
  "app": "https://github.com/LibreSprite/LibreSprite/",
  "version": "1.0-dev",
  "format": "RGBA8888",
  "size": { "w": 48, "h": 48 },
  "scale": "1",
  "frameTags": [
  ],
  "layers": [
   { "name": "bed", "opacity": 255 },
   { "name": "scape", "opacity": 255 },
   { "name": "scape-shadow", "opacity": 255},
   { "name": "Layer 1", "opacity": 160 }
  ]
 }
}
